vasca/__init__.py
vasca/_version.py
vasca/columns.py
vasca/field.py
vasca/field_ids.yaml
vasca/region.py
vasca/resource_manager.py
vasca/source.py
vasca/tables.py
vasca/tables_dict.py
vasca/utils.py
vasca/vasca_cfg.yaml
vasca/vasca_cfg_GCK.yaml
vasca/vasca_cfg_TDS.yaml
vasca/vasca_pipe.py
vasca/visualization.py
vasca/resource_metadata/resource_catalog.yml
vasca/resource_metadata/resource_envs.yml
vasca/test/__init__.py
vasca/test/test_pipeline.py
vasca/test/test_rm_config_files.py
vasca/test/test_utils.py
vasca/test/resources/GALEX_visits_list.fits
vasca/test/resources/GALEX_visits_list.info
vasca/test/resources/vasca_test_cfg.yaml
vasca/test/resources/6371091720297250816/MAST_6371091720297250816_FUV_coadd.fits
vasca/test/resources/6371091720297250816/MAST_6371091720297250816_FUV_data.fits
vasca/test/resources/6371091720297250816/MAST_6371091720297250816_FUV_down.ecsv
vasca/test/resources/6371091720297250816/MAST_6371091720297250816_NUV_coadd.fits
vasca/test/resources/6371091720297250816/MAST_6371091720297250816_NUV_data.fits
vasca/test/resources/6371091720297250816/MAST_6371091720297250816_NUV_down.ecsv
vasca/test/resources/6371091720297250816/mastDownload/GALEX/6371091582858297344/AIS_5_0001_sg40-xd-mcat.fits.gz
vasca/test/resources/6371091720297250816/mastDownload/GALEX/6371091582891851776/AIS_5_0002_sg40-xd-mcat.fits.gz
vasca/test/resources/6371091720297250816/mastDownload/GALEX/6371091720297250816/AIS_5_sg40-fd-int.fits.gz
vasca/test/resources/6371091720297250816/mastDownload/GALEX/6371091720297250816/AIS_5_sg40-nd-int.fits.gz
vasca/test/resources/6371091720297250816/mastDownload/GALEX/6371091720297250816/AIS_5_sg40-xd-mcat.fits.gz
vasca/test/resources/6388191295067652096/MAST_6388191295067652096_NUV_coadd.fits
vasca/test/resources/6388191295067652096/MAST_6388191295067652096_NUV_data.fits
vasca/test/resources/6388191295067652096/MAST_6388191295067652096_NUV_down.ecsv
vasca-1.0.16.dist-info/LICENSE
vasca-1.0.16.dist-info/METADATA
vasca-1.0.16.dist-info/WHEEL
vasca-1.0.16.dist-info/entry_points.txt
vasca-1.0.16.dist-info/top_level.txt
vasca-1.0.16.dist-info/RECORD
