Metadata-Version: 2.1
Name: vasca
Version: 1.0.16
Summary: Ultraviolet Variability Analysis is an astronomy pipeline for time-variable sources.
Author-email: Julian Schliwinski <julian.schliwinski@desy.de>, Rolf Bühler <rolf.buehler@desy.de>
License: BSD 3-Clause License
Project-URL: homepage, https://schliwiju.github.io/vasca-mirror/
Project-URL: documentation, https://schliwiju.github.io/vasca-mirror/
Project-URL: repository, https://github.com/rbuehler/vasca
Project-URL: changelog, https://tbd.desy.de
Keywords: astronomy,ultraviolet,pipeline
Requires-Python: >=3.10
License-File: LICENSE
Requires-Dist: astropy~=5.3
Requires-Dist: astroquery~=0.4.6
Requires-Dist: coverage~=7.2.7
Requires-Dist: healpy~=1.17
Requires-Dist: loguru~=0.7.0
Requires-Dist: matplotlib~=3.7.1
Requires-Dist: numpy~=1.24.3
Requires-Dist: pandas~=2.0.2
Requires-Dist: pytest~=7.3.1
Requires-Dist: pytest-cov~=4.1.0
Requires-Dist: python-dotenv~=1.0.0
Requires-Dist: PyYAML~=6.0
Requires-Dist: scikit-learn~=1.3.0
Requires-Dist: setuptools~=67.8.0
Requires-Dist: setuptools-scm
Requires-Dist: regions~=0.7
Requires-Dist: pyyaml-include~=1.3
Requires-Dist: ipywidgets~=8.0.6
Requires-Dist: ipympl~=0.9.3
Requires-Dist: jupyterlab~=4.0.2
Requires-Dist: sphinx~=7.2.6
Requires-Dist: myst-nb
Requires-Dist: furo
Requires-Dist: sphinx-autodoc2
Requires-Dist: sphinx-copybutton
Requires-Dist: sphinx-tippy
Requires-Dist: jupytext
Requires-Dist: itables
